{
  "pools": [
    {
      "rolls": 1,
      "entries": [
        {
          "type": "item",
          "name": "nameless_trinkets:missing_page"
        },
        {
          "type": "item",
          "name": "nameless_trinkets:reverse_card"
        },
        {
          "type": "item",
          "name": "nameless_trinkets:experience_battery"
        },
        {
          "type": "item",
          "name": "ironchest:crystal_chest"
        },
        {
          "type": "item",
          "name": "nameless_trinkets:experience_magnet"
        },
        {
          "type": "item",
          "name": "nameless_trinkets:broken_magnet"
        },
        {
          "type": "item",
          "name": "nameless_trinkets:super_magnet"
        },
        {
          "type": "item",
          "name": "nameless_trinkets:what_magnet"
        },
        {
          "type": "item",
          "name": "nameless_trinkets:callus"
        },
        {
          "type": "item",
          "name": "nameless_trinkets:speed_force"
        },
        {
          "type": "item",
          "name": "nameless_trinkets:vampire_blood"
        },
        {
          "type": "item",
          "name": "nameless_trinkets:lucky_rock"
        },
        {
          "type": "item",
          "name": "nameless_trinkets:vampire_blood"
        },
        {
          "type": "item",
          "name": "nameless_trinkets:puffer_fish_liver"
        },
        {
          "type": "item",
          "name": "nameless_trinkets:rage_mind"
        },
        {
          "type": "item",
          "name": "nameless_trinkets:tick"
        },
        {
          "type": "item",
          "name": "nameless_trinkets:blindfold"
        },
        {
          "type": "item",
          "name": "nameless_trinkets:explosion_proof_jacket"
        },
        {
          "type": "item",
          "name": "nameless_trinkets:cracked_crown"
        },
        {
          "type": "item",
          "name": "nameless_trinkets:ghast_eye"
        },
        {
          "type": "item",
          "name": "nameless_trinkets:wooden_stick"
        },
        {
          "type": "item",
          "name": "nameless_trinkets:blaze_nucleus"
        },
        {
          "type": "item",
          "name": "nameless_trinkets:ice_cube"
        },
        {
          "type": "item",
          "name": "nameless_trinkets:sigil_of_baphomet"
        },
        {
          "type": "item",
          "name": "nameless_trinkets:creeper_sense"
        },
        {
          "type": "item",
          "name": "nameless_trinkets:fertilizer"
        },
        {
          "type": "item",
          "name": "nameless_trinkets:gods_crown"
        },
        {
          "type": "item",
          "name": "nameless_trinkets:amphibious_hands"
        },
        {
          "type": "item",
          "name": "nameless_trinkets:tear_of_the_sea"
        },
        {
          "type": "item",
          "name": "nameless_trinkets:gills"
        },
        {
          "type": "item",
          "name": "nameless_trinkets:true_heart_of_the_sea"
        },
        {
          "type": "item",
          "name": "nameless_trinkets:moon_stone"
        },
        {
          "type": "item",
          "name": "nameless_trinkets:lucky_horseshoe"
        },
        {
          "type": "item",
          "name": "nameless_trinkets:sleeping_pills"
        },
        {
          "type": "item",
          "name": "nameless_trinkets:mysterious_trinket"
        }
      ]
    }
  ]
}
